aixplain_pipelines/__init__.py
aixplain_pipelines/__version__.py
aixplain_pipelines/aixplain_pipelines.py
aixplain_pipelines/execution.py
aixplain_pipelines/utils/__init__.py
aixplain_pipelines/utils/config.py
tests/__init__.py
tests/pipeline_test.py
utils/__init__.py
utils/config.py
aixplain_pipelines-0.0.4.dist-info/METADATA
aixplain_pipelines-0.0.4.dist-info/WHEEL
aixplain_pipelines-0.0.4.dist-info/top_level.txt
aixplain_pipelines-0.0.4.dist-info/RECORD
