Metadata-Version: 2.1
Name: aixplain-pipelines
Version: 0.0.4
Summary: aiXplain Pipelines adds AI functions to software.
Home-page: https://github.com/aixplain/pipelines/tree/main/docs
Author: Thiago Castro Ferriera and Duraikrishna Selvaraju
Author-email: thiago.ferreira@aixplain.com, krishna.durai@aixplain.com
License: http://www.apache.org/licenses/LICENSE-2.0
Project-URL: Documentation, https://github.com/aixplain/pipelines/tree/main/docs
Project-URL: Source, https://github.com/aixplain/pipelines
Platform: UNKNOWN
Classifier: Development Status :: 2 - Pre-Alpha
Classifier: Environment :: Web Environment
Classifier: Intended Audience :: Developers
Classifier: License :: OSI Approved :: Apache Software License
Classifier: Natural Language :: English
Classifier: Operating System :: OS Independent
Classifier: Programming Language :: Python
Classifier: Programming Language :: Python :: 3
Classifier: Programming Language :: Python :: 3.5
Classifier: Programming Language :: Python :: 3.6
Classifier: Programming Language :: Python :: 3.7
Classifier: Programming Language :: Python :: 3.8
Classifier: Programming Language :: Python :: 3.9
Classifier: Programming Language :: Python :: 3.10
Classifier: Programming Language :: Python :: 3.11
Classifier: Programming Language :: Python :: 3 :: Only
Classifier: Programming Language :: Python :: Implementation :: CPython
Classifier: Programming Language :: Python :: Implementation :: PyPy
Classifier: Topic :: Internet :: WWW/HTTP
Classifier: Topic :: Software Development :: Libraries
Requires-Python: >=3.5, <4
Requires-Dist: requests (>=2.1.0)
Requires-Dist: tqdm (>=4.1.0)
